racad.py
racad-0.1.2.dist-info/LICENSE
racad-0.1.2.dist-info/METADATA
racad-0.1.2.dist-info/WHEEL
racad-0.1.2.dist-info/top_level.txt
racad-0.1.2.dist-info/RECORD
