Metadata-Version: 2.1
Name: racad
Version: 0.1.2
Summary: Runtime Access for Class Attribute Docstrings
Author-email: Lucas Steinmann <lucas@steinm.net>
License: MIT License
Project-URL: Source, https://github.com/Lucas-Steinmann/racad
Project-URL: Issues, https://github.com/Lucas-Steinmann/racad/issues
Classifier: Programming Language :: Python
Classifier: Programming Language :: Python :: 3
Classifier: Programming Language :: Python :: 3.8
Classifier: Programming Language :: Python :: 3.9
Classifier: Programming Language :: Python :: 3.10
Classifier: Programming Language :: Python :: 3.11
Classifier: Programming Language :: Python :: 3.12
Classifier: Programming Language :: Python :: 3.13
Classifier: License :: OSI Approved :: MIT License
Classifier: Operating System :: OS Independent
Classifier: Development Status :: 4 - Beta
Classifier: Intended Audience :: Developers
Classifier: Topic :: Documentation
Classifier: Topic :: Software Development :: Libraries
Classifier: Topic :: Software Development :: Documentation
Requires-Python: >=3.8
License-File: LICENSE
